trustworthyai_vision/__init__.py
trustworthyai_vision/version.py
trustworthyai_vision/common/__init__.py
trustworthyai_vision/common/constants.py
trustworthyai_vision/common/interfaces.py
trustworthyai_vision/managers/__init__.py
trustworthyai_vision/managers/error_analysis_manager.py
trustworthyai_vision/managers/explainer_manager.py
trustworthyai_vision/tai_vision_insights/__init__.py
trustworthyai_vision/tai_vision_insights/tai_vision_insights.py
trustworthyai_vision/utils/__init__.py
trustworthyai_vision/utils/feature_extractors.py
trustworthyai_vision/utils/image_reader.py
trustworthyai_vision/utils/image_utils.py
trustworthyai_vision-0.3.10.dist-info/METADATA
trustworthyai_vision-0.3.10.dist-info/WHEEL
trustworthyai_vision-0.3.10.dist-info/top_level.txt
trustworthyai_vision-0.3.10.dist-info/RECORD
