Metadata-Version: 2.1
Name: trustworthyai_vision
Version: 0.3.10
Summary: SDK API to assess image Machine Learning models.
Home-page: https://github.com/affectlog/trustworthy-ai-toolbox
Author: AL360°
Author-email: developer@affectlog.com
Classifier: Programming Language :: Python :: 3.7
Classifier: Programming Language :: Python :: 3.8
Classifier: Programming Language :: Python :: 3.9
Classifier: License :: OSI Approved :: MIT License
Classifier: Operating System :: OS Independent
Classifier: Development Status :: 3 - Alpha
Requires-Python: >=3.7
Requires-Dist: numpy<2.0.0,>=1.17.2
Requires-Dist: pandas<2.0.0,>=0.25.1
Requires-Dist: scikit-learn>=0.22.1
Requires-Dist: scipy>=1.4.1
Requires-Dist: semver~=2.13.0
Requires-Dist: trustworthyai>=0.0.0
Requires-Dist: torchmetrics[detection]
Requires-Dist: vision-explanation-methods
Requires-Dist: Pillow<10.0.0; python_version <= "3.7"
Requires-Dist: Pillow>=10.0.0; python_version > "3.7"
